{"title":"다음 뉴스 ─ 팩트체크","url":"https://focus.daum.net/ch/news/factcheck","favicon":"https://t1.daumcdn.net/top/kakao/favicon.ico","elements":[{"title":"[팩트체크] 일본이 외국인 입국 완화 대상에서 한국을 제외했다?","contents":"(서울=연합뉴스) 장하나 기자 = 전 세계 국가들이 코로나19 팬데믹(세계적 대유행) 여파로 걸어 잠근 빗장을 속속 풀고 있는 가운데 일본도 외국인에 대한 입국·검역 규제 완화에 나서고 있다. 이런 가운데 국내 일부 언론은 6일 일본 TBS 보도 등을 인용해 일본이 미국과 영국, 프랑스 등 106개국에 대한 입국 거부 조치를 8일부터 해제하기로 했다고 전하","link":"https://v.daum.net/v/20220407180559527","retrieved":1649323360825},{"title":"\"국가부채 2200조, GDP 역전\" 언론의 '반복된 거짓' [오마이팩트]","contents":"[김시연, 김예진 기자] &nbsp;        ▲ &nbsp;얼마 전까지 올해 나랏빚(국가부채)이 1000조를 돌파한다고 보도했던 언론은 최근 국가부채가 2000조를 돌파해 GDP를 초월했다고 보도했다.    ⓒ 한국언론진흥재단 빅카인즈  &nbsp; [검증대상] \"국가부채 2200조, GDP 역전\" 언론 보도 &nbsp;&nbsp;- 나랏빗 1000조인데... 추가세수 퍼주기 급급한 정치권(&lt;국","link":"https://v.daum.net/v/20220407133606030","retrieved":1649308895431},{"title":"[팩트체크] 아시아에서 '성평등 나라' 1순위는 한국?","contents":"[앵커] 여성가족부를 없애는 공약 관련해서 일각에선 우리나라의 성평등지수가 아시아에서 가장 좋다, 그러니까 가장 평등한 나라다, 이런 주장이 나왔습니다. 사실인지 따져보겠습니다. 이지은 기자, 이 말이 어디서 나온 거죠? [기자] 지난 대선에서 국민의힘 공동선대위원장을 맡았던 이수정 교수가 한 토론회에서 한 말입니다. 들어보시죠. [이수정/경기대 범죄심리학","link":"https://v.daum.net/v/20220406204309236","retrieved":1649248875105},{"title":"[알고보니] 장애인 이동권, 장애인들 '집단이기주의'?","contents":"[뉴스데스크] ◀ 기자 ▶ 알고보니 시작합니다. 며칠 전 장애인들의 지하철역 삭발 시위에서 이런 항의가 나왔습니다. [지하철 이용객] \"장애인들 확실하게 돈 내고 무임승차하지 말고, 돈 내고 하면 엘리베이터 다 깔릴 거예요.\" 장애인에게 승강기가 필요하다면, 지하철 요금부터 내라는 건데요. 온라인 게시판이나 댓글에서도 일부 누리꾼들은 \"장애인들의 시위는","link":"https://v.daum.net/v/20220406202215855","retrieved":1649248875107},{"title":"[사실은] 푸틴, 전범 재판 법정에 세울 수 있을까","contents":"우크라이나 수도 키이우 근처에서 참혹하게 숨진 민간인들 시신 수백 구가 수습됐습니다. 러시아군이 점령했던 '부차'라는 지역입니다. 옷이 벗겨지거나 손이 묶이고, 고문을 당한 흔적이 뚜렷한 시신들도 상당수로 알려졌는데, 국제 사회는 러시아가 민간을 학살한 명백한 증거라며 분노하고 있습니다. 물론, 러시아는 영상이 조작됐다며 학살을 부인하고 있습니다. 바이든","link":"https://v.daum.net/v/20220406174807113","retrieved":1649237068334},{"title":"[팩트체크] 한국이 수출한 의류 때문에 중국에서 코로나 감염?","contents":"(서울=연합뉴스) 박성제 기자 유경민 인턴기자 = 중국에서 코로나19가 확산하는 가운데 현지 언론은 한국에서 수입한 의류를 감염원 중 하나로 보도했다. 중국 관영 매체인 글로벌타임스는 4일 베이징 차오양구에서 8건의 코로나19 신규 감염 사례가 발생했는데 한국에서 수입한 의류와 관련이 있다고 했다. 중국공산당 기관지 인민일보 산하 매체인 건강시보도 랴오닝성","link":"https://v.daum.net/v/20220406174001875","retrieved":1649237068339},{"title":"[뉴스AS] 산림청 산불 대책이 토목 사업?..\"자연림·토양수분 늘려야\"","contents":"지난달 31일 산림청이 발표한 ‘2022년 경북·강원 대형 산불 시사점 분석 및 개선대책’은 ‘산불예방 숲가꾸기’ 2배 확대, 연 350㏊ 규모의 내화수림대(불에 강한 활엽수 등의 지대) 조성을 주요 내용으로 한다. 최근 강원·경북 일대의 산불 대책으로, 방안대로라면 산림 내 임도(산림관리용 길)도 2030년까지 현재 157㎞에서 6357㎞로 확대되고, 물","link":"https://v.daum.net/v/20220406140604797","retrieved":1649226462780},{"title":"[팩트체크K] 확진 이력자 \"해외여행 쉽지 않네\"..어떻게 갈 수 있을까?","contents":"코로나19의 국내 유입을 차단하기 위해 인천국제공항 입국장에 설치됐던 방역 관련 시설이 지난  1일 철거됐습니다. 지난해 4월 해외 입국여행객 분리를 위해 설치된 지 1년 만입니다. 이로써 인천공항 입국장 운영체계는 코로나19 이전 수준으로 돌아갔습니다. 앞서 지난달 21일부터 백신 접종을 완료한 뒤 국내로 들어오는 해외 입국자의 자가격리도 면제됐습니다.","link":"https://v.daum.net/v/20220405070110098","retrieved":1649111007959},{"title":"[팩트체크] \"코로나 시신 염 안 하겠다\"..진짜 감염되나","contents":"[앵커] 거리두기가 한 번 더 완화되면서 그간 화장이 권고됐던 코로나19 사망자 시신에 대해서도 유족이 원하면 매장할 수 있게 됐습니다. 그런데, 장례업계에선 \"매장할 때, 바이러스가 시신에 남아 있으면 어쩌나\"라면서 불안해하고 있습니다. 30여 곳의 장례식장이 '염습 거부' 입장까지 밝히고 있습니다. 팩트체크를 해보겠습니다. 이지은 기자, 시신으로 코로나","link":"https://v.daum.net/v/20220404211703505","retrieved":1649076009346},{"title":"[팩트체크] '대표이사 알박기 논란' 대우조선해양은 공기업?","contents":"(서울=연합뉴스) 이웅 기자 = 대우조선해양 대표이사 선임 논란이 정권 교체기 신구(新舊) 권력 간의 알력을 키우는 모습이다. 원일희 대통령직인수위원회 수석부대변인은 지난 1일 대우조선해양을 \"국민 혈세 4조1천억 원이 투입된 부실 공기업\"으로 지칭하며 박두선 신임 대표이사 선임이 '현 정부의 알박기 인사'라는 입장을 고수했다. 반면 청와대는 \"민간기업 인","link":"https://v.daum.net/v/20220404181708981","retrieved":1649064183538}]}